analysis.py
cli.py
collector.py
collector_europe.py
collector_worldwide.py
database.py
grid.py
waze_client.py
waze_logs-1.2.2.dist-info/licenses/LICENSE
web/app.py
web/templates/index.html
waze_logs-1.2.2.dist-info/METADATA
waze_logs-1.2.2.dist-info/WHEEL
waze_logs-1.2.2.dist-info/entry_points.txt
waze_logs-1.2.2.dist-info/top_level.txt
waze_logs-1.2.2.dist-info/RECORD
