Metadata-Version: 2.4
Name: waze-logs
Version: 1.2.2
Summary: Worldwide Waze traffic event collection and analysis tool - demonstrates location privacy risks in crowdsourced traffic applications
Author-email: jasperan <jasperan@users.noreply.github.com>
Maintainer-email: jasperan <jasperan@users.noreply.github.com>
License: MIT
Project-URL: Homepage, https://github.com/jasperan/waze-osint-tracker
Project-URL: Repository, https://github.com/jasperan/waze-osint-tracker
Project-URL: Issues, https://github.com/jasperan/waze-osint-tracker/issues
Keywords: waze,traffic,privacy,osint,geolocation,security-research,data-collection
Classifier: Development Status :: 4 - Beta
Classifier: Environment :: Console
Classifier: Intended Audience :: Developers
Classifier: Intended Audience :: Science/Research
Classifier: License :: OSI Approved :: MIT License
Classifier: Operating System :: OS Independent
Classifier: Programming Language :: Python :: 3
Classifier: Programming Language :: Python :: 3.10
Classifier: Programming Language :: Python :: 3.11
Classifier: Programming Language :: Python :: 3.12
Classifier: Topic :: Security
Classifier: Topic :: Scientific/Engineering :: Information Analysis
Requires-Python: >=3.10
License-File: LICENSE
Requires-Dist: click>=8.0
Requires-Dist: requests>=2.28
Requires-Dist: pyyaml>=6.0
Requires-Dist: tabulate>=0.9
Requires-Dist: flask>=2.0
Requires-Dist: rich>=13.0
Provides-Extra: dev
Requires-Dist: pytest>=7.0; extra == "dev"
Dynamic: license-file
